pymbse/microservice/__init__.py
pymbse/microservice/api.py
pymbse/query/__init__.py
pymbse/query/api.py
pymbse/query/config/__init__.py
pymbse/query/config/hash_functions.py
pymbse/query/config/model_type.py
pymbse/query/config/notebook_script_config.py
pymbse/query/config/numpy_encoder.py
pymbse/query/config/pymbse_config.py
pymbse/query/design_variables.py
pymbse/query/model_api/__init__.py
pymbse/query/model_api/executor/__init__.py
pymbse/query/model_api/executor/executor.py
pymbse/query/model_api/executor/gitlab_executor.py
pymbse/query/model_api/executor/notebook_converter.py
pymbse/query/model_api/executor/notebook_script_executor.py
pymbse/query/model_api/model_api.py
pymbse/query/model_api/model_api_factory.py
pymbse/query/model_api/notebook_script_api.py
pymbse/query/model_api/snapshot/__init__.py
pymbse/query/model_api/snapshot/model_snapshot.py
pymbse/setup.py
pymbse-0.0.22.dist-info/WHEEL
pymbse-0.0.22.dist-info/METADATA
pymbse-0.0.22.dist-info/RECORD
